AUTHORS.rst
CONTRIBUTING.rst
HISTORY.rst
LICENSE
MANIFEST.in
README.rst
setup.cfg
setup.py
docs/Makefile
docs/authors.rst
docs/conf.py
docs/contributing.rst
docs/history.rst
docs/index.rst
docs/installation.rst
docs/make.bat
docs/readme.rst
docs/usage.rst
spark_dataloader/__init__.py
spark_dataloader/rdbms_ingestion.py
spark_dataloader.egg-info/PKG-INFO
spark_dataloader.egg-info/SOURCES.txt
spark_dataloader.egg-info/dependency_links.txt
spark_dataloader.egg-info/entry_points.txt
spark_dataloader.egg-info/not-zip-safe
spark_dataloader.egg-info/requires.txt
spark_dataloader.egg-info/top_level.txt
spark_dataloader/cli/__init__.py
spark_dataloader/cli/full_ingestion.py
spark_dataloader/cli/incremental_append_ingestion.py
spark_dataloader/cli/incremental_merge_ingestion.py
tests/__init__.py
tests/populate_incremental_append.py
tests/populate_incremental_merge.py
tests/test_full_ingest.sh
tests/test_incremental_append.py
tests/test_incremental_merge.py
tests/test_spark_dataloader.py