Metadata-Version: 2.1
Name: spark-dataloader
Version: 0.1.3
Summary: Standard data loaders for Apache Spark
Home-page: https://gitlab.com/kagesenshi/spark_dataloader
Author: Izhar Firdaus
Author-email: kagesenshi.87@gmail.com
License: Apache Software License 2.0
Keywords: spark_dataloader
Platform: UNKNOWN
Classifier: Development Status :: 2 - Pre-Alpha
Classifier: Intended Audience :: Developers
Classifier: License :: OSI Approved :: Apache Software License
Classifier: Natural Language :: English
Classifier: Programming Language :: Python :: 3
Classifier: Programming Language :: Python :: 3.6
Classifier: Programming Language :: Python :: 3.7
Classifier: Programming Language :: Python :: 3.8
Requires-Python: >=3.6
License-File: LICENSE
License-File: AUTHORS.rst
